steamprofile/__init__.py
steamprofile/core.py
steamprofile-0.1.3.dist-info/licenses/LICENSE
steamprofile-0.1.3.dist-info/licenses/LICENSE.txt
steamprofile-0.1.3.dist-info/METADATA
steamprofile-0.1.3.dist-info/WHEEL
steamprofile-0.1.3.dist-info/top_level.txt
steamprofile-0.1.3.dist-info/RECORD
