Metadata-Version: 2.4
Name: steamprofile
Version: 0.1.3
Summary: Gather information about steam profiles
Author-email: Aaron Levi Can <aaronlevican@gmail.com>
License-Expression: MIT
Project-URL: Homepage, https://github.com/aaronlyy/steamprofile
Project-URL: Issues, https://github.com/aaronlyy/steamprofile/issues
Requires-Python: >=3.6
License-File: LICENSE
License-File: LICENSE.txt
Requires-Dist: requests
Requires-Dist: Unidecode
Dynamic: license-file
